sequential_ckts/traffic_light_controller_basic/sig_control.v
`define TRUE 1'b1
`define FALSE 1'b0
`define Y2R_DELAY 3
`define R2G_DELAY 2

/*
>State Zero: Highway= Green Country= Red
-State One: Highway= Yellow Country= Red
*State Two: Highway= Red Country= Red
@State Three: Highway= Red Country= Green
=State Four: Highway= Red Country= Yellow
*/



module sig_control (output reg [1:0] hwy, cntry,
                    input wire x, clk, clear
    
);

parameter   RED= 2'd0,
            YELLOW= 2'd1,
            GREEN= 2'd2,

            S0= 3'd0, 
            S1= 3'd1,
            S2= 3'd2,
            S3= 3'd3,
            S4= 3'd4;
    
reg [2:0] state, next_state;

always @(posedge clk) begin
    if (clear) state<= S0;
    else state<= next_state;
end

always @(state, x) begin
    case (state)
        S0: next_state<= (x ? S1 : S0);
        S1: begin
            repeat(`Y2R_DELAY) @(posedge clk);
            next_state<= S2;
        end 
        S2: begin
            repeat(`R2G_DELAY) @(posedge clk);
            next_state<= S3;    
        end
        S3: next_state<= (x ? S3 : S4);
        S4: begin
            repeat(`Y2R_DELAY) @(posedge clk);
            next_state<= S0;
        end
        default: next_state<= S0;
        endcase
end

always @(state) begin
    case (state)
        S0: {hwy,cntry}={GREEN, RED};
        S1: {hwy,cntry}={YELLOW, RED};
        S2: {hwy,cntry}={RED, RED};
        S3: {hwy,cntry}={RED, GREEN};
        S4: {hwy,cntry}={RED, YELLOW};
        default: {hwy,cntry}={GREEN, RED};
    endcase
end

endmodule //sig_control

sequential_ckts/traffic_light_controller_basic/sig_control_tb.v
`timescale 1ns/1ps 
`include "sig_control.v"

module sig_control_tb (
    
);

wire [1:0] hwy, cntry;
reg x, clk, clear;

sig_control s1(hwy, cntry, x, clk, clear);

initial begin
    clk= `FALSE;
    forever #5 clk= ~clk;
end

initial begin
    $dumpfile("sig_control_tb.vcd");
    $dumpvars(0, sig_control_tb);
end

initial begin
    clear= `TRUE;
    repeat(5) @(negedge clk);
    clear= `FALSE;
end

initial begin
    x= `FALSE;
    repeat(20) @(negedge clk); x= `TRUE;    //20 times the clock cycle 
    repeat(10) @(negedge clk); x= `FALSE;   //20 times the clock cycle
    
    repeat(20) @(negedge clk); x= `TRUE;
    repeat(10) @(negedge clk); x= `FALSE;
    
    repeat(20) @(negedge clk); x= `TRUE;
    repeat(10) @(negedge clk); x= `FALSE;

    repeat(10) @(negedge clk); $finish;
end 

endmodule //sig_control_tb

sequential_ckts/traffic_light_controller_basic/sig_control_tb.vcd
$date
	Tue Oct 06 14:11:25 2020
$end
$version
	Icarus Verilog
$end
$timescale
	1ps
$end
$scope module sig_control_tb $end
$var wire 2 ! hwy [1:0] $end
$var wire 2 " cntry [1:0] $end
$var reg 1 # clear $end
$var reg 1 $ clk $end
$var reg 1 % x $end
$scope module s1 $end
$var wire 1 # clear $end
$var wire 1 $ clk $end
$var wire 1 % x $end
$var reg 2 & cntry [1:0] $end
$var reg 2 ' hwy [1:0] $end
$var reg 3 ( next_state [2:0] $end
$var reg 3 ) state [2:0] $end
$upscope $end
$upscope $end
$enddefinitions $end
#0
$dumpvars
bx )
b0 (
bx '
bx &
0%
0$
1#
bx "
bx !
$end
#5000
b10 !
b10 '
b0 "
b0 &
b0 )
1$
#10000
0$
#15000
1$
#20000
0$
#25000
1$
#30000
0$
#35000
1$
#40000
0$
#45000
1$
#50000
0#
0$
#55000
1$
#60000
0$
#65000
1$
#70000
0$
#75000
1$
#80000
0$
#85000
1$
#90000
0$
#95000
1$
#100000
0$
#105000
1$
#110000
0$
#115000
1$
#120000
0$
#125000
1$
#130000
0$
#135000
1$
#140000
0$
#145000
1$
#150000
0$
#155000
1$
#160000
0$
#165000
1$
#170000
0$
#175000
1$
#180000
0$
#185000
1$
#190000
0$
#195000
1$
#200000
b1 (
1%
0$
#205000
b1 !
b1 '
b1 )
1$
#210000
0$
#215000
1$
#220000
0$
#225000
1$
#230000
0$
#235000
b10 (
1$
#240000
0$
#245000
b0 !
b0 '
b10 )
1$
#250000
0$
#255000
1$
#260000
0$
#265000
b11 (
1$
#270000
0$
#275000
b10 "
b10 &
b11 )
1$
#280000
0$
#285000
1$
#290000
0$
#295000
1$
#300000
b100 (
0%
0$
#305000
b1 "
b1 &
b100 )
1$
#310000
0$
#315000
1$
#320000
0$
#325000
1$
#330000
0$
#335000
b0 (
1$
#340000
0$
#345000
b10 !
b10 '
b0 "
b0 &
b0 )
1$
#350000
0$
#355000
1$
#360000
0$
#365000
1$
#370000
0$
#375000
1$
#380000
0$
#385000
1$
#390000
0$
#395000
1$
#400000
0$
#405000
1$
#410000
0$
#415000
1$
#420000
0$
#425000
1$
#430000
0$
#435000
1$
#440000
0$
#445000
1$
#450000
0$
#455000
1$
#460000
0$
#465000
1$
#470000
0$
#475000
1$
#480000
0$
#485000
1$
#490000
0$
#495000
1$
#500000
b1 (
1%
0$
#505000
b1 !
b1 '
b1 )
1$
#510000
0$
#515000
1$
#520000
0$
#525000
1$
#530000
0$
#535000
b10 (
1$
#540000
0$
#545000
b0 !
b0 '
b10 )
1$
#550000
0$
#555000
1$
#560000
0$
#565000
b11 (
1$
#570000
0$
#575000
b10 "
b10 &
b11 )
1$
#580000
0$
#585000
1$
#590000
0$
#595000
1$
#600000
b100 (
0%
0$
#605000
b1 "
b1 &
b100 )
1$
#610000
0$
#615000
1$
#620000
0$
#625000
1$
#630000
0$
#635000
b0 (
1$
#640000
0$
#645000
b10 !
b10 '
b0 "
b0 &
b0 )
1$
#650000
0$
#655000
1$
#660000
0$
#665000
1$
#670000
0$
#675000
1$
#680000
0$
#685000
1$
#690000
0$
#695000
1$
#700000
0$
#705000
1$
#710000
0$
#715000
1$
#720000
0$
#725000
1$
#730000
0$
#735000
1$
#740000
0$
#745000
1$
#750000
0$
#755000
1$
#760000
0$
#765000
1$
#770000
0$
#775000
1$
#780000
0$
#785000
1$
#790000
0$
#795000
1$
#800000
b1 (
1%
0$
#805000
b1 !
b1 '
b1 )
1$
#810000
0$
#815000
1$
#820000
0$
#825000
1$
#830000
0$
#835000
b10 (
1$
#840000
0$
#845000
b0 !
b0 '
b10 )
1$
#850000
0$
#855000
1$
#860000
0$
#865000
b11 (
1$
#870000
0$
#875000
b10 "
b10 &
b11 )
1$
#880000
0$
#885000
1$
#890000
0$
#895000
1$
#900000
b100 (
0%
0$
#905000
b1 "
b1 &
b100 )
1$
#910000
0$
#915000
1$
#920000
0$
#925000
1$
#930000
0$
#935000
b0 (
1$
#940000
0$
#945000
b10 !
b10 '
b0 "
b0 &
b0 )
1$
