sequential_ckts/basic_vending_machine/NEWSPAPER_VENDING.v
`timescale 1ns/1ps 
//newspaper vending machine coin acceptor
//using a FSM approach
module NEWSPAPER_VENDING (
    output wire newspaper,
    input wire [1:0] coin,
    input clk, reset 
);

wire [1:0] NEXT_STATE;
reg [1:0] PRES_STATE;

//state encodings
parameter   s0= 2'b00,
            s5= 2'b01,
            s10= 2'b10,
            s15= 2'b11;

//clock the state flip-flops use synchronous reset
always @(posedge clk) begin
    if(reset== 1'b1)
        PRES_STATE<= s0;
    else
        PRES_STATE<= NEXT_STATE;
end

//re-evaluate combinational logic each time
//a coin is put or present state changes.
assign {newspaper, NEXT_STATE}= fsm(coin, PRES_STATE);

//combination logic
function [2:0] fsm(
    input [1:0] fsm_coin, 
    input [1:0] fsm_PRES_STATE
    );
    reg fsm_newspaper;
    reg [1:0] fsm_next_state;

    begin
        case (fsm_PRES_STATE)
            s0: begin
                if(fsm_coin== 2'b10)
                begin
                    fsm_newspaper= 1'b0;
                    fsm_next_state= s10;
                end
                else if(fsm_coin== 2'b01) begin
                    fsm_newspaper= 1'b0;
                    fsm_next_state= s5;
                end
                else begin
                    fsm_newspaper= 1'b0;
                    fsm_next_state= s0;
                end
            end

            s5: begin
                if (fsm_coin== 2'b10) begin
                    fsm_newspaper= 1'b0;
                    fsm_next_state= s15;
                end
                else if (fsm_coin== 2'b01) begin
                    fsm_newspaper= 1'b0;
                    fsm_next_state= s10;
                end
                else begin
                    fsm_newspaper= 1'b0;
                    fsm_next_state= s5;
                end
            end

            s10: begin
                if(fsm_coin== 2'b10) begin
                    fsm_newspaper= 1'b0;
                    fsm_next_state= s15;
                end
                else if (fsm_coin== 2'b01) begin
                    fsm_newspaper= 1'b0;
                    fsm_next_state= s15;
                end
                else begin
                    fsm_newspaper= 1'b0;
                    fsm_next_state= s10;
                end
            end

            s15: begin
                fsm_newspaper= 1'b1;
                fsm_next_state= s0;
            end
            default: begin
                fsm_newspaper= 1'b0;
                fsm_next_state= s0;
            end
        endcase
        fsm= {fsm_newspaper, fsm_next_state};
    end
endfunction
 
endmodule //NEWSPAPER_VENDING

sequential_ckts/basic_vending_machine/NEWSPAPER_VENDING_tb.v
`timescale 1ns/1ps 
`include "NEWSPAPER_VENDING.v"
module NEWSPAPER_VENDING_tb (
    
);

reg clock;
reg[1:0] coin;
reg reset;
wire newspaper;

//instantiating the vending machine
NEWSPAPER_VENDING n0(newspaper, coin, clock, reset);

initial begin
    clock= 1'b0;
    forever #20 clock= ~clock;
end

initial begin

    $dumpfile("NEWSPAPER_VENDING_tb.vcd");
    $dumpvars(0, NEWSPAPER_VENDING_tb);
    coin= 2'b00;
    reset= 1'b1;
    #50 reset= 1'b0;
    @(negedge clock);
    //wait for the negative edge of the clock

    //put 3 nickles to get newspaper
    #80 coin= 2'b01; #40 coin= 2'b00;
    #80 coin= 2'b01; #40 coin= 2'b00;
    #80 coin= 2'b01; #40 coin= 2'b00;

    //put 1 nickle and 1 dime
    #180 coin= 2'b01; #40 coin= 2'b00;
    #80 coin= 2'b10; #40 coin= 2'b00;

    //put 2 dimes but machine does not return nickle 
    //as change
    #180 coin= 2'b10; #40 coin= 2'b00;
    #80 coin= 2'b10; #40 coin= 2'b00;

    //put one dime and then one nickle
    #180 coin= 2'b10; #40 coin= 2'b00;
    #80 coin= 2'b01; #40 coin= 2'b00;

    #70 $finish;
end

endmodule //NEWSPAPER_VENDING_tb

sequential_ckts/basic_vending_machine/NEWSPAPER_VENDING_tb.vcd
$date
	Tue Nov 17 22:42:58 2020
$end
$version
	Icarus Verilog
$end
$timescale
	1ps
$end
$scope module NEWSPAPER_VENDING_tb $end
$var wire 1 ! newspaper $end
$var reg 1 " clock $end
$var reg 2 # coin [1:0] $end
$var reg 1 $ reset $end
$scope module n0 $end
$var wire 1 " clk $end
$var wire 2 % coin [1:0] $end
$var wire 1 $ reset $end
$var wire 1 ! newspaper $end
$var wire 2 & NEXT_STATE [1:0] $end
$var reg 2 ' PRES_STATE [1:0] $end
$scope function fsm $end
$var reg 2 ( fsm_PRES_STATE [1:0] $end
$var reg 2 ) fsm_coin [1:0] $end
$var reg 1 * fsm_newspaper $end
$var reg 2 + fsm_next_state [1:0] $end
$upscope $end
$upscope $end
$upscope $end
$enddefinitions $end
#0
$dumpvars
b0 +
0*
b0 )
bx (
bx '
b0 &
b0 %
1$
b0 #
0"
0!
$end
#20000
b0 (
b0 '
1"
#40000
0"
#50000
0$
#60000
1"
#80000
0"
#100000
1"
#120000
0"
#140000
1"
#160000
b1 &
b1 +
b1 )
0"
b1 #
b1 %
#180000
b10 &
b10 +
b1 (
b1 '
1"
#200000
b1 &
b1 +
b0 )
0"
b0 #
b0 %
#220000
1"
#240000
0"
#260000
1"
#280000
b10 &
b10 +
b1 )
0"
b1 #
b1 %
#300000
b11 &
b11 +
b10 (
b10 '
1"
#320000
b10 &
b10 +
b0 )
0"
b0 #
b0 %
#340000
1"
#360000
0"
#380000
1"
#400000
b11 &
b11 +
b1 )
0"
b1 #
b1 %
#420000
b0 &
1!
b0 +
1*
b11 (
b11 '
1"
#440000
b0 )
0"
b0 #
b0 %
#460000
0!
0*
b0 (
b0 '
1"
#480000
0"
#500000
1"
#520000
0"
#540000
1"
#560000
0"
#580000
1"
#600000
0"
#620000
b1 &
b1 +
b1 )
1"
b1 #
b1 %
#640000
0"
#660000
b1 (
b1 '
b1 &
b1 +
b0 )
1"
b0 #
b0 %
#680000
0"
#700000
1"
#720000
0"
#740000
b11 &
b11 +
b10 )
1"
b10 #
b10 %
#760000
0"
#780000
1!
1*
b11 (
b11 '
b0 &
b0 +
b0 )
1"
b0 #
b0 %
#800000
0"
#820000
0!
0*
b0 (
b0 '
1"
#840000
0"
#860000
1"
#880000
0"
#900000
1"
#920000
0"
#940000
1"
#960000
b10 &
b10 +
b10 )
0"
b10 #
b10 %
#980000
b11 &
b11 +
b10 (
b10 '
1"
#1000000
b10 &
b10 +
b0 )
0"
b0 #
b0 %
#1020000
1"
#1040000
0"
#1060000
1"
#1080000
b11 &
b11 +
b10 )
0"
b10 #
b10 %
#1100000
b0 &
1!
b0 +
1*
b11 (
b11 '
1"
#1120000
b0 )
0"
b0 #
b0 %
#1140000
0!
0*
b0 (
b0 '
1"
#1160000
0"
#1180000
1"
#1200000
0"
#1220000
1"
#1240000
0"
#1260000
1"
#1280000
0"
#1300000
b10 &
b10 +
b10 )
1"
b10 #
b10 %
#1320000
0"
#1340000
b10 (
b10 '
b10 &
b10 +
b0 )
1"
b0 #
b0 %
#1360000
0"
#1380000
1"
#1400000
0"
#1420000
b11 &
b11 +
b1 )
1"
b1 #
b1 %
#1440000
0"
#1460000
1!
1*
b11 (
b11 '
b0 &
b0 +
b0 )
1"
b0 #
b0 %
#1480000
0"
#1500000
0!
0*
b0 (
b0 '
1"
