nptel_eg/register_banks/register_bank_v1.v
`timescale 1ns/1ps
//4x32 register file
module register_bank_v1 (
    output reg [31:0] rdData1, rdData2,
    input wire [1:0] sr1, sr2, dr,
    input wire [31:0] wrData,
    input clk, write
);

reg [31:0] R0, R1, R2, R3;

always @(*) begin
    case(sr1)
    00: rdData1= R0;
    01: rdData1= R1;
    10: rdData1= R2;
    11: rdData1= R3;
    default: rdData1= 32'hxxxx_xxxx;
    endcase
end

always @(*) begin
    case (sr2)
        00: rdData2= R0;
        01: rdData2= R1;
        10: rdData2= R2;
        11: rdData2= R3; 
        default: rdData2= 32'hxxxx_xxxx;
    endcase
end

always @(posedge clk) begin
    if(write) begin
        case (dr)
            00: R0<= wrData;
            01: R1<= wrData;
            10: R2<= wrData;
            11: R3<= wrData;
        endcase
    end
end

endmodule //register_bank_v1

nptel_eg/register_banks/register_bank_v2.v
//32x32 register file
module register_bank_v2 (
    output wire [31:0] rdData1, rdData2,
    input  wire [4:0] sr1, sr2, dr,
    input wire [31:0] wrData,
    input wire clk, write, reset
);

integer k;
reg [31:0] regfile [0:31];

assign rdData1= regfile[sr1];
assign rdData2= regfile[sr2];

always @(posedge clk) begin
    if (reset) begin
        for (k=0; k<32; k=k+1) begin
            regfile[k]<= 0;
        end
    end
    else if(write)
    regfile[dr]<= wrData;
end

endmodule //register_bank_v2

nptel_eg/register_banks/register_bank_tb.v
`timescale 1ns/1ps 
`include "register_bank_v2.v"
`include "register_bank_v1.v"

module register_bank_tb (
    
);

wire [31:0] rdData1, rdData2;
reg [4:0] sr1, sr2, dr;
reg [31:0] wrData;
reg clk, write, reset;

integer k;

//register_bank_v1 v1(rdData1, rdData2, sr1, sr2, dr, wrData, clk, write);
//when instantiating the register bank v1
//remove the terminal reset.

register_bank_v2 v2(rdData1, rdData2, sr1, sr2, dr, wrData, clk, write, reset); 

initial begin
    clk= 1'b0;
    forever #5 clk= !clk;
end

initial begin
    $dumpfile("register_bank_tb.vcd");
    $dumpvars(0, register_bank_tb);

    #1 reset= 1'b1; write= 1'b0;
    #5 reset= 1'b0; 
end

initial begin
    #7 for (k=0; k<32; k=k+1) begin
        dr= k; wrData= (10*k); write= 1'b1;
        #10 write= 1'b0;
    end

    #20 for(k=0; k<32; k=k+2) begin
        sr1= k; sr2= k+1;
        #5;
        $display("reg[%2d]= %d, reg[%2d]= %d", sr1, rdData1, sr2, rdData2);
    end
    #50 $finish;
end

endmodule //register_bank_tb

nptel_eg/register_banks/register_bank_tb.vcd
$date
	Wed Nov 18 18:23:06 2020
$end
$version
	Icarus Verilog
$end
$timescale
	1ps
$end
$scope module register_bank_tb $end
$var wire 32 ! rdData2 [31:0] $end
$var wire 32 " rdData1 [31:0] $end
$var reg 1 # clk $end
$var reg 5 $ dr [4:0] $end
$var reg 1 % reset $end
$var reg 5 & sr1 [4:0] $end
$var reg 5 ' sr2 [4:0] $end
$var reg 32 ( wrData [31:0] $end
$var reg 1 ) write $end
$var integer 32 * k [31:0] $end
$scope module v2 $end
$var wire 1 # clk $end
$var wire 5 + dr [4:0] $end
$var wire 32 , rdData1 [31:0] $end
$var wire 32 - rdData2 [31:0] $end
$var wire 1 % reset $end
$var wire 5 . sr1 [4:0] $end
$var wire 5 / sr2 [4:0] $end
$var wire 32 0 wrData [31:0] $end
$var wire 1 ) write $end
$var integer 32 1 k [31:0] $end
$upscope $end
$upscope $end
$enddefinitions $end
#0
$dumpvars
bx 1
bx 0
bx /
bx .
bx -
bx ,
bx +
bx *
x)
bx (
bx '
bx &
x%
bx $
0#
bx "
bx !
$end
#1000
0)
1%
#5000
b100000 1
1#
#6000
0%
#7000
1)
b0 (
b0 0
b0 $
b0 +
b0 *
#10000
0#
#15000
1#
#17000
b1010 (
b1010 0
b1 $
b1 +
b1 *
1)
#20000
0#
#25000
1#
#27000
b10100 (
b10100 0
b10 $
b10 +
b10 *
1)
#30000
0#
#35000
1#
#37000
b11110 (
b11110 0
b11 $
b11 +
b11 *
1)
#40000
0#
#45000
1#
#47000
b101000 (
b101000 0
b100 $
b100 +
b100 *
1)
#50000
0#
#55000
1#
#57000
b110010 (
b110010 0
b101 $
b101 +
b101 *
1)
#60000
0#
#65000
1#
#67000
b111100 (
b111100 0
b110 $
b110 +
b110 *
1)
#70000
0#
#75000
1#
#77000
b1000110 (
b1000110 0
b111 $
b111 +
b111 *
1)
#80000
0#
#85000
1#
#87000
b1010000 (
b1010000 0
b1000 $
b1000 +
b1000 *
1)
#90000
0#
#95000
1#
#97000
b1011010 (
b1011010 0
b1001 $
b1001 +
b1001 *
1)
#100000
0#
#105000
1#
#107000
b1100100 (
b1100100 0
b1010 $
b1010 +
b1010 *
1)
#110000
0#
#115000
1#
#117000
b1101110 (
b1101110 0
b1011 $
b1011 +
b1011 *
1)
#120000
0#
#125000
1#
#127000
b1111000 (
b1111000 0
b1100 $
b1100 +
b1100 *
1)
#130000
0#
#135000
1#
#137000
b10000010 (
b10000010 0
b1101 $
b1101 +
b1101 *
1)
#140000
0#
#145000
1#
#147000
b10001100 (
b10001100 0
b1110 $
b1110 +
b1110 *
1)
#150000
0#
#155000
1#
#157000
b10010110 (
b10010110 0
b1111 $
b1111 +
b1111 *
1)
#160000
0#
#165000
1#
#167000
b10100000 (
b10100000 0
b10000 $
b10000 +
b10000 *
1)
#170000
0#
#175000
1#
#177000
b10101010 (
b10101010 0
b10001 $
b10001 +
b10001 *
1)
#180000
0#
#185000
1#
#187000
b10110100 (
b10110100 0
b10010 $
b10010 +
b10010 *
1)
#190000
0#
#195000
1#
#197000
b10111110 (
b10111110 0
b10011 $
b10011 +
b10011 *
1)
#200000
0#
#205000
1#
#207000
b11001000 (
b11001000 0
b10100 $
b10100 +
b10100 *
1)
#210000
0#
#215000
1#
#217000
b11010010 (
b11010010 0
b10101 $
b10101 +
b10101 *
1)
#220000
0#
#225000
1#
#227000
b11011100 (
b11011100 0
b10110 $
b10110 +
b10110 *
1)
#230000
0#
#235000
1#
#237000
b11100110 (
b11100110 0
b10111 $
b10111 +
b10111 *
1)
#240000
0#
#245000
1#
#247000
b11110000 (
b11110000 0
b11000 $
b11000 +
b11000 *
1)
#250000
0#
#255000
1#
#257000
b11111010 (
b11111010 0
b11001 $
b11001 +
b11001 *
1)
#260000
0#
#265000
1#
#267000
b100000100 (
b100000100 0
b11010 $
b11010 +
b11010 *
1)
#270000
0#
#275000
1#
#277000
b100001110 (
b100001110 0
b11011 $
b11011 +
b11011 *
1)
#280000
0#
#285000
1#
#287000
b100011000 (
b100011000 0
b11100 $
b11100 +
b11100 *
1)
#290000
0#
#295000
1#
#297000
b100100010 (
b100100010 0
b11101 $
b11101 +
b11101 *
1)
#300000
0#
#305000
1#
#307000
b100101100 (
b100101100 0
b11110 $
b11110 +
b11110 *
1)
#310000
0#
#315000
1#
#317000
b100110110 (
b100110110 0
b11111 $
b11111 +
b11111 *
1)
#320000
0#
#325000
1#
#327000
b100000 *
0)
#330000
0#
#335000
1#
#340000
0#
#345000
1#
#347000
b1010 !
b1010 -
b1 '
b1 /
b0 "
b0 ,
b0 &
b0 .
b0 *
#350000
0#
#352000
b11110 !
b11110 -
b11 '
b11 /
b10100 "
b10100 ,
b10 &
b10 .
b10 *
#355000
1#
#357000
b110010 !
b110010 -
b101 '
b101 /
b101000 "
b101000 ,
b100 &
b100 .
b100 *
#360000
0#
#362000
b1000110 !
b1000110 -
b111 '
b111 /
b111100 "
b111100 ,
b110 &
b110 .
b110 *
#365000
1#
#367000
b1011010 !
b1011010 -
b1001 '
b1001 /
b1010000 "
b1010000 ,
b1000 &
b1000 .
b1000 *
#370000
0#
#372000
b1101110 !
b1101110 -
b1011 '
b1011 /
b1100100 "
b1100100 ,
b1010 &
b1010 .
b1010 *
#375000
1#
#377000
b10000010 !
b10000010 -
b1101 '
b1101 /
b1111000 "
b1111000 ,
b1100 &
b1100 .
b1100 *
#380000
0#
#382000
b10010110 !
b10010110 -
b1111 '
b1111 /
b10001100 "
b10001100 ,
b1110 &
b1110 .
b1110 *
#385000
1#
#387000
b10101010 !
b10101010 -
b10001 '
b10001 /
b10100000 "
b10100000 ,
b10000 &
b10000 .
b10000 *
#390000
0#
#392000
b10111110 !
b10111110 -
b10011 '
b10011 /
b10110100 "
b10110100 ,
b10010 &
b10010 .
b10010 *
#395000
1#
#397000
b11010010 !
b11010010 -
b10101 '
b10101 /
b11001000 "
b11001000 ,
b10100 &
b10100 .
b10100 *
#400000
0#
#402000
b11100110 !
b11100110 -
b10111 '
b10111 /
b11011100 "
b11011100 ,
b10110 &
b10110 .
b10110 *
#405000
1#
#407000
b11111010 !
b11111010 -
b11001 '
b11001 /
b11110000 "
b11110000 ,
b11000 &
b11000 .
b11000 *
#410000
0#
#412000
b100001110 !
b100001110 -
b11011 '
b11011 /
b100000100 "
b100000100 ,
b11010 &
b11010 .
b11010 *
#415000
1#
#417000
b100100010 !
b100100010 -
b11101 '
b11101 /
b100011000 "
b100011000 ,
b11100 &
b11100 .
b11100 *
#420000
0#
#422000
b100110110 !
b100110110 -
b11111 '
b11111 /
b100101100 "
b100101100 ,
b11110 &
b11110 .
b11110 *
#425000
1#
#427000
b100000 *
