nptel_eg/MIPS_32_PROC/pipe_MIPS32.v
`timescale 1ns/1ps 
//pipelined implementation of MIPS 32-bit processor.
//pipelined satges are micro-instructions:
/*
->Stage1: Instruction Fetch (IF)
->Stage2: Instruction Decode (ID)
->Stage3: Execute (EX)
->Stage4: Memeory Operation (MEM)
->Stage5: Write Back (WB)

PC: Program Counter
NPC: New Program Counter
IR: Instruction Register
Imm: Immediate Data Register
LMD: Load Memory Data

*/

module pipe_MIPS32 (
    input wire clk1, clk2                  //two-phase clock
);

reg [31:0] PC, IF_ID_IR, IF_ID_NPC;                                 //stage 1-pipelined flip-flops

reg [31:0] ID_EX_IR, ID_EX_NPC, ID_EX_A, ID_EX_B, ID_EX_Imm;        //stage 2-pipeline flip-flops

reg [2:0] ID_EX_type, EX_MEM_type, MEM_WB_type;                     //flip-flops to determine the type of instruction

reg [31:0] EX_MEM_IR, EX_MEM_ALUOut, EX_MEM_B;                      //satge 3-pipeline flip-flops
reg EX_MEM_cond;

reg [31:0] MEM_WB_IR, MEM_WB_ALUOut, MEM_WB_LMD;                    //stage 4-pipeline flip-flops

reg [31:0] Reg [0:31];                                              //Register bank(32x32)
reg [31:0] Mem [0:1023];                                            //1024 x 32 memory

parameter   ADD= 6'd0,
            SUB= 6'd1,
            AND= 6'd2,
            OR= 6'd3,
            SLT= 6'd4,
            MUL= 6'd5,
            HLT= 6'b11_1111,
            LW= 6'd8,
            SW= 6'd9,
            ADDI= 6'd10,
            SUBI= 6'd11,
            SLTI= 6'd12,
            BNEQZ= 6'd13,
            BEQZ= 6'd14;                                        //OPCODES for instructions

parameter   RR_ALU= 3'b000,
            RM_ALU= 3'b001,
            LOAD= 3'b010,
            STORE= 3'b011,
            BRANCH= 3'b100,
            HALT= 3'b101;                                       //type of instructions

reg HALTED;                                                     //set after HLT instruction is 
                                                                //completed (in WB stage)

reg TAKEN_BRANCH;                                               //required to disable instructions
                                                                // after branch

//pipeline stage-1 
//Instruction Fetch (IF)
always @(posedge clk1) begin
    if(HALTED== 0) begin
        if (((EX_MEM_IR[31:26]== BEQZ) && (EX_MEM_cond== 1)) || 
        ((EX_MEM_IR[31:26]== BNEQZ) && (EX_MEM_cond== 0))) begin
            IF_ID_IR <=          Mem[EX_MEM_ALUOut];
            TAKEN_BRANCH<=      1'b1;
            IF_ID_NPC<=         EX_MEM_ALUOut+1;
            PC<=                EX_MEM_ALUOut+1;
        end
        else begin
            IF_ID_IR<= Mem[PC];
            IF_ID_NPC<= PC+1;
            PC<= PC+1;
        end
    end
end

//pipeline stage-2
//Instruction Decode (ID)
always @(posedge clk2) begin
    if(HALTED== 0) begin
        if(IF_ID_IR[25:21]== 5'b00000) begin
            ID_EX_A<= 0;
        end
        else ID_EX_A<= Reg[IF_ID_IR[25:21]];        //rs
    end
        if(IF_ID_IR[20:16]== 5'b00000) begin
            ID_EX_B<= 0;
        end
        else ID_EX_B<= Reg[IF_ID_IR[20:16]];        //rt

        ID_EX_NPC<= IF_ID_NPC;
        ID_EX_IR<= IF_ID_IR;
        ID_EX_Imm<= {{16{IF_ID_IR[15]}}, {IF_ID_IR[15:0]}};     //sign extention to Immediate register

        case (IF_ID_IR[31:26])
            ADD, SUB, AND, OR, SLT, MUL:    ID_EX_type<= RR_ALU;
            ADDI, SUBI, SLTI:               ID_EX_type<= RM_ALU;
            LW:                             ID_EX_type<= LOAD;
            SW:                             ID_EX_type<= STORE;
            BNEQZ, BEQZ:                    ID_EX_type<= BRANCH;
            HLT:                            ID_EX_type<= HALT;
            default:                        ID_EX_type<= HALT;
        endcase
end

//pipeline stage-3
//Execute (EX)
always @(posedge clk1) begin
    if (HALTED== 0) begin
        EX_MEM_type<= ID_EX_type;
        EX_MEM_IR<= ID_EX_IR;
        TAKEN_BRANCH<= 0;

        case (ID_EX_type)
            RR_ALU: begin
                case (ID_EX_IR[31:26])        //opcode
                    ADD:        EX_MEM_ALUOut<= ID_EX_A + ID_EX_B;
                    SUB:        EX_MEM_ALUOut<= ID_EX_A - ID_EX_B;
                    AND:        EX_MEM_ALUOut<= ID_EX_A & ID_EX_B;
                    OR:         EX_MEM_ALUOut<= ID_EX_A | ID_EX_B;
                    SLT:        EX_MEM_ALUOut<= ID_EX_A < ID_EX_B;
                    MUL:        EX_MEM_ALUOut<= ID_EX_A * ID_EX_B;
                    default:    EX_MEM_ALUOut<= 32'hxxxx_xxxx;
                endcase
            end

            RM_ALU: begin
                case (ID_EX_IR[31:26])      //opcode
                    ADDI:       EX_MEM_ALUOut<= ID_EX_A + ID_EX_Imm;
                    SUBI:       EX_MEM_ALUOut<= ID_EX_A - ID_EX_Imm;
                    SLTI:       EX_MEM_ALUOut<= ID_EX_A < ID_EX_Imm;
                    default:    EX_MEM_ALUOut<= 32'hxxxx_xxxx;
                endcase
            end

            LOAD, STORE: begin
                EX_MEM_ALUOut<= ID_EX_A + ID_EX_Imm;
                EX_MEM_B<=      ID_EX_B;
            end

            BRANCH: begin
                EX_MEM_ALUOut<=     ID_EX_NPC + ID_EX_Imm;
                EX_MEM_cond<=       (ID_EX_A== 0);
            end
        endcase
    end
end

//pipeline stage-4
//Memory(MEM)
always @(posedge clk2) begin
    if(HALTED== 0) begin
        MEM_WB_type<=   EX_MEM_type;
        MEM_WB_IR<=     EX_MEM_IR;

        case (EX_MEM_type)
            RR_ALU, RM_ALU:     MEM_WB_ALUOut<= EX_MEM_ALUOut;
            LOAD:               MEM_WB_LMD<= Mem[EX_MEM_ALUOut];
            STORE:              if (TAKEN_BRANCH== 0) begin     //disable write
                                Mem[EX_MEM_ALUOut]<= EX_MEM_B;
            end
        endcase
    end
end

//pipeline stage-5
//Write Back (WB)
always @(posedge clk1) begin
    if (TAKEN_BRANCH== 0) begin
        case (MEM_WB_type)
            RR_ALU:     Reg[MEM_WB_IR[15:11]]<= MEM_WB_ALUOut;      //rd
            RM_ALU:     Reg[MEM_WB_IR[20:16]]<= MEM_WB_ALUOut;      //rt
            LOAD:       Reg[MEM_WB_IR[20:16]]<= MEM_WB_LMD;         //rt
            HALT:       HALTED<= 1'b1;
        endcase
    end
end

endmodule //pipe_MIPS32

nptel_eg/MIPS_32_PROC/pipe_MIPS32_tb2.v
`timescale 1ns/1ps 
`include "pipe_MIPS32.v"
module pipe_MIPS32_tb2 (
    
);

reg clk1, clk2;
integer k;

pipe_MIPS32 mips(clk1, clk2);

initial begin
    clk1= 0; clk2= 0;
    repeat(50) begin            //two phase clock
        #5 clk1= 1; #5 clk1= 0;
        #5 clk2= 1; #5 clk2= 0; 
    end
end

initial begin
    for (k = 0; k<31; k= k+1) begin
        mips.Reg[k]= k;
    end

    mips.Mem[0]= 32'h28010078;      //ADDI R1, R0 120
    mips.Mem[1]= 32'h0c631800;      //OR R3, R3, R3  STALL CYCLE
    mips.Mem[2]= 32'h20220000;      //LW R2, 0(R1)
    mips.Mem[3]= 32'h0c631800;      //OR R3, R3, R3  STALL CYCLE
    mips.Mem[4]= 32'h2842002d;      //ADDI R2, R2, 45
    mips.Mem[5]= 32'h0c631800;      //OR R3, R3, R3  STALL CYCLE
    mips.Mem[6]= 32'h24220001;      //SW R2, 1(R1)
    mips.Mem[7]= 32'hfc000000;      //HLT

    mips.Mem[120]= 85;

    mips.PC= 0;
    mips.HALTED= 0;
    mips.TAKEN_BRANCH= 0;

    #225 $display("Mem[120]: %4d \nMem[121]: %4d", mips.Mem[120], mips.Mem[121]);
end

initial begin
    $dumpfile("pipe_MIPS32_tb2.vcd");
    $dumpvars(0, pipe_MIPS32_tb2);
    #245 $finish;
end

endmodule //pipe_MIPS32_tb2

nptel_eg/MIPS_32_PROC/pipe_MIPS32_tb2.vcd
$date
	Tue Dec 01 12:14:30 2020
$end
$version
	Icarus Verilog
$end
$timescale
	1ps
$end
$scope module pipe_MIPS32_tb2 $end
$var reg 1 ! clk1 $end
$var reg 1 " clk2 $end
$var integer 32 # k [31:0] $end
$scope module mips $end
$var wire 1 ! clk1 $end
$var wire 1 " clk2 $end
$var reg 32 $ EX_MEM_ALUOut [31:0] $end
$var reg 32 % EX_MEM_B [31:0] $end
$var reg 32 & EX_MEM_IR [31:0] $end
$var reg 1 ' EX_MEM_cond $end
$var reg 3 ( EX_MEM_type [2:0] $end
$var reg 1 ) HALTED $end
$var reg 32 * ID_EX_A [31:0] $end
$var reg 32 + ID_EX_B [31:0] $end
$var reg 32 , ID_EX_IR [31:0] $end
$var reg 32 - ID_EX_Imm [31:0] $end
$var reg 32 . ID_EX_NPC [31:0] $end
$var reg 3 / ID_EX_type [2:0] $end
$var reg 32 0 IF_ID_IR [31:0] $end
$var reg 32 1 IF_ID_NPC [31:0] $end
$var reg 32 2 MEM_WB_ALUOut [31:0] $end
$var reg 32 3 MEM_WB_IR [31:0] $end
$var reg 32 4 MEM_WB_LMD [31:0] $end
$var reg 3 5 MEM_WB_type [2:0] $end
$var reg 32 6 PC [31:0] $end
$var reg 1 7 TAKEN_BRANCH $end
$upscope $end
$upscope $end
$enddefinitions $end
#0
$dumpvars
07
b0 6
bx 5
bx 4
bx 3
bx 2
bx 1
bx 0
bx /
bx .
bx -
bx ,
bx +
bx *
0)
bx (
x'
bx &
bx %
bx $
b11111 #
0"
0!
$end
#5000
b1 6
b1 1
b101000000000010000000001111000 0
1!
#10000
0!
#15000
b1 /
b1111000 -
b101000000000010000000001111000 ,
b1 .
b1 +
b0 *
1"
#20000
0"
#25000
b1111000 $
b101000000000010000000001111000 &
b1 (
b10 6
b10 1
b1100011000110001100000000000 0
1!
#30000
0!
#35000
b1111000 2
b101000000000010000000001111000 3
b1 5
b0 /
b1100000000000 -
b1100011000110001100000000000 ,
b10 .
b11 +
b11 *
1"
#40000
0"
#45000
b11 6
b11 1
b100000001000100000000000000000 0
b11 $
b1100011000110001100000000000 &
b0 (
1!
#50000
0!
#55000
b10 /
b0 -
b100000001000100000000000000000 ,
b11 .
b10 +
b1111000 *
b11 2
b1100011000110001100000000000 3
b0 5
1"
#60000
0"
#65000
b10 %
b1111000 $
b100000001000100000000000000000 &
b10 (
b100 6
b100 1
b1100011000110001100000000000 0
1!
#70000
0!
#75000
b1010101 4
b100000001000100000000000000000 3
b10 5
b0 /
b1100000000000 -
b1100011000110001100000000000 ,
b100 .
b11 +
b11 *
1"
#80000
0"
#85000
b101 6
b101 1
b101000010000100000000000101101 0
b11 $
b1100011000110001100000000000 &
b0 (
1!
#90000
0!
#95000
b1 /
b101101 -
b101000010000100000000000101101 ,
b101 .
b1010101 +
b1010101 *
b1100011000110001100000000000 3
b0 5
1"
#100000
0"
#105000
b10000010 $
b101000010000100000000000101101 &
b1 (
b110 6
b110 1
b1100011000110001100000000000 0
1!
#110000
0!
#115000
b10000010 2
b101000010000100000000000101101 3
b1 5
b0 /
b1100000000000 -
b1100011000110001100000000000 ,
b110 .
b11 +
b11 *
1"
#120000
0"
#125000
b111 6
b111 1
b100100001000100000000000000001 0
b11 $
b1100011000110001100000000000 &
b0 (
1!
#130000
0!
#135000
b11 /
b1 -
b100100001000100000000000000001 ,
b111 .
b10000010 +
b1111000 *
b11 2
b1100011000110001100000000000 3
b0 5
1"
#140000
0"
#145000
b10000010 %
b1111001 $
b100100001000100000000000000001 &
b11 (
b1000 6
b1000 1
b11111100000000000000000000000000 0
1!
#150000
0!
#155000
b100100001000100000000000000001 3
b11 5
b101 /
b0 -
b11111100000000000000000000000000 ,
b1000 .
b0 +
b0 *
1"
#160000
0"
#165000
b1001 6
b1001 1
bx 0
b11111100000000000000000000000000 &
b101 (
1!
#170000
0!
#175000
bx -
bx ,
b1001 .
bx +
bx *
b11111100000000000000000000000000 3
b101 5
1"
#180000
0"
#185000
1)
bx &
b1010 6
b1010 1
1!
#190000
0!
#195000
b1010 .
1"
