nptel_eg/datapath_controlpath/signed_multiplication_using_booth_multiplier/BOOTH_controller.v
`timescale 1ns/1ps 
module BOOTH_controller (
    output reg LdA, clrA, sftA, LdQ, clrQ, sftQ, sftDff,
    LdM, clrff, add_sub, EnableALU, decr, LdCount, done,
    input wire clk, q0, qm1, start, eqz    
);

reg [2:0] state;
parameter   S0= 3'b000,
            S1= 3'b001,
            S2= 3'b010,
            S3= 3'b011,
            S4= 3'b100,
            S5= 3'b101,
            S6= 3'b110,
            S7= 3'b111;

always @(posedge clk) begin
    case (state)
        S0: if(start) state<= S1;
        S1: state<= S2;
        S2: begin @(posedge clk)
            if({q0, qm1}== 2'b01) state<= S3;
            else if({q0, qm1}== 2'b10) state<= S4;
            else state<= S5;
        end
        S3: state<= S5;
        S4: state<= S5;
        S5: state<= S7;
        S7: begin
            if(({q0, qm1}== 2'b01) && !eqz) state<= S3;
            else if(({q0, qm1}== 2'b10) && !eqz) state<= S4;
            else if(eqz) state<= S6; 
            else state<= S5;
        end
        S6: state<= S6;
        default: state<= S0;
    endcase
end

always @(state) begin
    case (state)
        S0: begin
            {LdA, clrA, sftA}= 3'b000; {LdQ, clrQ, sftQ}= 3'b000; {LdM, clrff, sftDff, done}= 4'b0000; 
            {add_sub, EnableALU, LdCount, decr}= 4'b0000;
        end
        S1: begin
            {LdA, clrA, sftA}= 3'b010; {LdQ, clrQ, sftQ}= 3'b010; {LdM, clrff, sftDff, done}= 4'b1100; 
            {add_sub, EnableALU, LdCount, decr}= 4'b0000;
        end
        S2: begin
            {LdA, clrA, sftA}= 3'b000; {LdQ, clrQ, sftQ}= 3'b100; {LdM, clrff, sftDff, done}= 4'b0000; 
            {add_sub, EnableALU, LdCount, decr}= 4'b0010;
        end
        S3: begin
            {LdA, clrA, sftA}= 3'b100; {LdQ, clrQ, sftQ}= 3'b000; {LdM, clrff, sftDff, done}= 4'b0000; 
            {add_sub, EnableALU, LdCount, decr}= 4'b1100;
        end
        S4: begin
            {LdA, clrA, sftA}= 3'b100; {LdQ, clrQ, sftQ}= 3'b000; {LdM, clrff, sftDff, done}= 4'b0000; 
            {add_sub, EnableALU, LdCount, decr}= 4'b0100;
        end
        S5: begin
            {LdA, clrA, sftA}= 3'b001; {LdQ, clrQ, sftQ}= 3'b001; {LdM, clrff, sftDff, done}= 4'b0010; 
            {add_sub, EnableALU, LdCount, decr}= 4'b0001;
        end
        S7: begin
            {LdA, clrA, sftA}= 3'b000; {LdQ, clrQ, sftQ}= 3'b000; {LdM, clrff, sftDff, done}= 4'b0000; 
            {add_sub, EnableALU, LdCount, decr}= 4'b0000;
        end
        S6: begin
            {LdA, clrA, sftA}= 3'b000; {LdQ, clrQ, sftQ}= 3'b000; {LdM, clrff, sftDff, done}= 4'b0001; 
            {add_sub, EnableALU, LdCount, decr}= 4'b0000;
        end
        default: begin
            {LdA, clrA, sftA}= 3'b000; {LdQ, clrQ, sftQ}= 3'b000; {LdM, clrff, sftDff, done}= 4'b0000; 
            {add_sub, EnableALU, LdCount, decr}= 4'b0000;
        end
    endcase
end

endmodule //BOOTH_controller

nptel_eg/datapath_controlpath/signed_multiplication_using_booth_multiplier/COUNTER.v
`timescale 1ns/1ps 
module COUNTER (
    output reg [3:0] data_out,
    input wire [3:0] LdCountValue,
    input wire decr, Ld, clk 
);

always @(posedge clk) begin
    if(Ld) data_out<= LdCountValue;
    else if (decr) data_out<= data_out-1;
end

endmodule //COUNTER

nptel_eg/datapath_controlpath/signed_multiplication_using_booth_multiplier/ALU.v
`timescale 1ns/1ps 
module ALU (
    output reg [4:0] out,
    input wire [4:0] in1, in2,
    input wire add_sub, EnableALU
);

always @(EnableALU) begin
    if(add_sub==0) out= in1-in2;
    //add when active high
    else out= in1+in2;
end
endmodule //ALU

nptel_eg/datapath_controlpath/signed_multiplication_using_booth_multiplier/PIPO.v
`timescale 1ns/1ps 
module PIPO (
    output reg [4:0] data_out,
    input wire [4:0] data_in,
    input wire clk, load 
);
//data_in is the multiplicand
integer i;
always @(posedge clk) begin
    if(load) data_out<= data_in;
end
endmodule //PIPO

nptel_eg/datapath_controlpath/signed_multiplication_using_booth_multiplier/DFF.v
`timescale 1ns/1ps 
module DFF (
    output reg q,
    input wire d, sft, clk, clr    
);

always @(posedge clk) begin
    if(clr) q<= 0;
    else if(sft) q<= d;
end

endmodule //DFF

nptel_eg/datapath_controlpath/signed_multiplication_using_booth_multiplier/SHIFTREG2.v
`timescale 1ns/ 1ps 
module SHIFTREG2 (
    output reg [4:0] data_out,
    output wire [3:0] LdCountValue, 
    input wire [4:0] data_in,
    input wire s_in, clk, Ld, clr, sft
);

integer i;

always @(posedge clk) begin
    if(clr) data_out<= 0;
    else if(Ld) data_out<= data_in;
    else if(sft) data_out<= {s_in, data_out[4:1]};
end

assign LdCountValue= no_of_multiplier_digits(data_in);

function [3:0] no_of_multiplier_digits(input [4:0] datat_in);
    begin
        no_of_multiplier_digits= 3'b101;
        /*
        for (i= 4; i>= 0; i= i-1) begin
            if(data_in[i]!= 0) begin
                no_of_multiplier_digits= i+1; 
                i= 0;
            end 
        end
        */
    end
endfunction

endmodule //SHIFTREG2

nptel_eg/datapath_controlpath/signed_multiplication_using_booth_multiplier/SHIFTREG1.v
`timescale 1ns/ 1ps 
module SHIFTREG1 (
    output reg [4:0] data_out,
    input wire [4:0] data_in,
    input wire s_in, clk, Ld, clr, sft
);

always @(posedge clk) begin
    if(clr) data_out<= 0;
    else if(Ld) data_out<= data_in;
    else if(sft) data_out<= {s_in, data_out[4:1]};
end

endmodule //SHIFTREG1

nptel_eg/datapath_controlpath/signed_multiplication_using_booth_multiplier/BOOTH_datapath.v
`timescale 1ns/1ps 
`include "SHIFTREG1.v"
`include "SHIFTREG2.v"
`include "DFF.v"
`include "PIPO.v"
`include "ALU.v"
`include "COUNTER.v"

module BOOTH_datapath (
    output wire q0, qm1, eqz,
    output wire [9:0] data_out, 
    input wire [4:0] data_in,
    input wire LdA, LdQ, LdM, clrA, clrQ, clrff, 
    sftA, sftQ, sftDff, add_sub, EnableALU, clk, LdCount, decr 
);

wire [4:0] A, M, Q, Z;
wire [3:0] LdCountValue;
wire [3:0] count;

assign eqz= ~|count;
assign data_out= {A, Q};
assign q0= Q[0];

SHIFTREG1 REG_A(A, Z, A[4], clk, LdA, clrA, sftA);
//A[15] -sign of the register A to be carry forwarded for 
//the next iterations after the shift right operation is 
//performed.
SHIFTREG2 REG_Q(Q, LdCountValue, data_in, A[0], clk, LdQ, clrQ, sftQ);
//A[0]- LSB of the register A which is to be shifted to 
//the next register Q which stores the multiplier.
DFF QM1(qm1, Q[0], sftDff, clk, clrff);
//the dff input is Q[0] which is the LSB of register Q
//the multiplier.
PIPO REG_M(M, data_in, clk, LdM);
ALU AL(Z, A, M, add_sub, EnableALU);
COUNTER CN(count, LdCountValue, decr, LdCount,  clk);

endmodule //BOOTH_datapath

nptel_eg/datapath_controlpath/signed_multiplication_using_booth_multiplier/top.v
`timescale 1ns/1ps 
/*
top module to instantiate the fundamental blocks of
signed multiplication using Booth multiplication
1.shift register A
2.shift register Q
3.dff
4.PIPO M
5.ALU
6.COUNTER
*/
`include "BOOTH_datapath.v"
`include "BOOTH_controller.v"

module top (
    output wire done,
    output wire [9:0] MUL_result,
    input wire [4:0] data_in, 
    input wire start, clk 
);

wire    LdA, clrA, sftA,
        LdQ, clrQ, sftQ,
        clrff, sftDff,
        LdM,
        q0, qm1,
        LdCount, decr,
        add_sub, EnableALU,
        eqz;

BOOTH_datapath DAT(
    .eqz(eqz),

    .LdA(LdA),
    .clrA(clrA),
    .sftA(sftA),

    .LdQ(LdQ),
    .clrQ(clrQ),
    .sftQ(sftQ),

    .LdM(LdM),
    .clrff(clrff),
    .sftDff(sftDff),
    
    .add_sub(add_sub),
    .EnableALU(EnableALU),

    .q0(q0),
    .qm1(qm1),
    
    .LdCount(LdCount),
    .decr(decr),

    .data_in(data_in),
    .data_out(MUL_result),
    
    .clk(clk)
);

BOOTH_controller CTRL(
    .eqz(eqz),
    
    .LdA(LdA),
    .clrA(clrA),
    .sftA(sftA),
    
    .LdQ(LdQ),
    .clrQ(clrQ),
    .sftQ(sftQ),

    .LdM(LdM),
    .clrff(clrff),
    .sftDff(sftDff),
    
    .add_sub(add_sub),
    .EnableALU(EnableALU),
    
    .q0(q0),
    .qm1(qm1),
    
    .LdCount(LdCount),
    .decr(decr),
    
    .start(start),
    .done(done),
    .clk(clk)
);

endmodule //top

nptel_eg/datapath_controlpath/signed_multiplication_using_booth_multiplier/top_tb.v
`timescale 1ns/1ps 
`include "top.v"

module top_tb (
    
);

wire done;
wire [9:0] MUL_result;
reg [4:0] data_in;
reg start, clk;

top t0(done, MUL_result, data_in, start, clk);

initial begin
    clk= 1'b0;
    forever #5 clk= ~clk;
end

initial begin
    $dumpfile("top_tb.vcd");
    $dumpvars(0, top_tb);

    start= 1'b1;
    data_in= 5'b10110;
    #26 data_in= 5'd13;
    #200 $finish;
end

endmodule //top_tb

nptel_eg/datapath_controlpath/signed_multiplication_using_booth_multiplier/top_tb.vcd
$date
	Mon Nov 16 13:04:07 2020
$end
$version
	Icarus Verilog
$end
$timescale
	1ps
$end
$scope module top_tb $end
$var wire 1 ! done $end
$var wire 10 " MUL_result [9:0] $end
$var reg 1 # clk $end
$var reg 5 $ data_in [4:0] $end
$var reg 1 % start $end
$scope module t0 $end
$var wire 1 # clk $end
$var wire 5 & data_in [4:0] $end
$var wire 1 % start $end
$var wire 1 ' sftQ $end
$var wire 1 ( sftDff $end
$var wire 1 ) sftA $end
$var wire 1 * qm1 $end
$var wire 1 + q0 $end
$var wire 1 , eqz $end
$var wire 1 ! done $end
$var wire 1 - decr $end
$var wire 1 . clrff $end
$var wire 1 / clrQ $end
$var wire 1 0 clrA $end
$var wire 1 1 add_sub $end
$var wire 10 2 MUL_result [9:0] $end
$var wire 1 3 LdQ $end
$var wire 1 4 LdM $end
$var wire 1 5 LdCount $end
$var wire 1 6 LdA $end
$var wire 1 7 EnableALU $end
$scope module CTRL $end
$var wire 1 # clk $end
$var wire 1 % start $end
$var wire 1 * qm1 $end
$var wire 1 + q0 $end
$var wire 1 , eqz $end
$var reg 1 7 EnableALU $end
$var reg 1 6 LdA $end
$var reg 1 5 LdCount $end
$var reg 1 4 LdM $end
$var reg 1 3 LdQ $end
$var reg 1 1 add_sub $end
$var reg 1 0 clrA $end
$var reg 1 / clrQ $end
$var reg 1 . clrff $end
$var reg 1 - decr $end
$var reg 1 ! done $end
$var reg 1 ) sftA $end
$var reg 1 ( sftDff $end
$var reg 1 ' sftQ $end
$var reg 3 8 state [2:0] $end
$upscope $end
$scope module DAT $end
$var wire 1 7 EnableALU $end
$var wire 1 6 LdA $end
$var wire 1 5 LdCount $end
$var wire 1 4 LdM $end
$var wire 1 3 LdQ $end
$var wire 1 1 add_sub $end
$var wire 1 # clk $end
$var wire 1 0 clrA $end
$var wire 1 / clrQ $end
$var wire 1 . clrff $end
$var wire 5 9 data_in [4:0] $end
$var wire 1 - decr $end
$var wire 1 ) sftA $end
$var wire 1 ( sftDff $end
$var wire 1 ' sftQ $end
$var wire 1 * qm1 $end
$var wire 1 + q0 $end
$var wire 1 , eqz $end
$var wire 10 : data_out [9:0] $end
$var wire 4 ; count [3:0] $end
$var wire 5 < Z [4:0] $end
$var wire 5 = Q [4:0] $end
$var wire 5 > M [4:0] $end
$var wire 4 ? LdCountValue [3:0] $end
$var wire 5 @ A [4:0] $end
$scope module AL $end
$var wire 1 7 EnableALU $end
$var wire 1 1 add_sub $end
$var wire 5 A in2 [4:0] $end
$var wire 5 B in1 [4:0] $end
$var reg 5 C out [4:0] $end
$upscope $end
$scope module CN $end
$var wire 1 5 Ld $end
$var wire 1 # clk $end
$var wire 1 - decr $end
$var wire 4 D LdCountValue [3:0] $end
$var reg 4 E data_out [3:0] $end
$upscope $end
$scope module QM1 $end
$var wire 1 # clk $end
$var wire 1 . clr $end
$var wire 1 F d $end
$var wire 1 ( sft $end
$var reg 1 * q $end
$upscope $end
$scope module REG_A $end
$var wire 1 6 Ld $end
$var wire 1 # clk $end
$var wire 1 0 clr $end
$var wire 5 G data_in [4:0] $end
$var wire 1 H s_in $end
$var wire 1 ) sft $end
$var reg 5 I data_out [4:0] $end
$upscope $end
$scope module REG_M $end
$var wire 1 # clk $end
$var wire 5 J data_in [4:0] $end
$var wire 1 4 load $end
$var reg 5 K data_out [4:0] $end
$upscope $end
$scope module REG_Q $end
$var wire 1 3 Ld $end
$var wire 1 # clk $end
$var wire 1 / clr $end
$var wire 5 L data_in [4:0] $end
$var wire 1 M s_in $end
$var wire 1 ' sft $end
$var wire 4 N LdCountValue [3:0] $end
$var reg 5 O data_out [4:0] $end
$scope function no_of_multiplier_digits $end
$var reg 5 P datat_in [4:0] $end
$upscope $end
$upscope $end
$upscope $end
$upscope $end
$upscope $end
$enddefinitions $end
#0
$dumpvars
b10110 P
bx O
b101 N
xM
b10110 L
bx K
b10110 J
bx I
xH
bx G
xF
bx E
b101 D
bx C
bx B
bx A
bx @
b101 ?
bx >
bx =
bx <
bx ;
bx :
b10110 9
bx 8
x7
x6
x5
x4
x3
bx 2
x1
x0
x/
x.
x-
x,
x+
x*
x)
x(
x'
b10110 &
1%
b10110 $
0#
bx "
x!
$end
#5000
01
07
05
0-
04
0.
0(
0!
03
0/
0'
06
00
0)
b0 8
1#
#10000
0#
#15000
14
1.
1/
10
b1 8
1#
#20000
0#
#25000
0M
0H
0F
0+
15
04
0.
13
0/
00
b0 @
b0 B
b0 I
b0 "
b0 2
b0 :
b0 =
b0 O
0*
b10110 >
b10110 A
b10110 K
b10 8
1#
#26000
b1101 P
b1101 $
b1101 &
b1101 9
b1101 J
b1101 L
#30000
0#
#35000
1F
1+
0,
b101 ;
b101 E
b1101 "
b1101 2
b1101 :
b1101 =
b1101 O
1#
#40000
0#
#45000
b1010 <
b1010 C
b1010 G
17
05
03
16
b100 8
1#
#50000
0#
#55000
b10100 <
b10100 C
b10100 G
07
1-
1(
1'
06
1)
b101 8
b101001101 "
b101001101 2
b101001101 :
b1010 @
b1010 B
b1010 I
1#
#60000
0#
#65000
1M
0F
0+
0-
0(
0'
0)
b101 @
b101 B
b101 I
b10100110 "
b10100110 2
b10100110 :
b110 =
b110 O
1*
b100 ;
b100 E
b111 8
1#
#70000
0#
#75000
b11011 <
b11011 C
b11011 G
11
17
16
b11 8
1#
#80000
0#
#85000
b101 <
b101 C
b101 G
1H
01
07
1-
1(
1'
06
1)
b1101100110 "
b1101100110 2
b1101100110 :
b11011 @
b11011 B
b11011 I
b101 8
1#
#90000
0#
#95000
0-
0(
0'
0)
1F
1+
b111 8
b11 ;
b11 E
0*
b10011 =
b10011 O
b1110110011 "
b1110110011 2
b1110110011 :
b11101 @
b11101 B
b11101 I
1#
#100000
0#
#105000
b111 <
b111 C
b111 G
17
16
b100 8
1#
#110000
0#
#115000
b10001 <
b10001 C
b10001 G
07
1-
1(
1'
06
1)
0H
b101 8
b11110011 "
b11110011 2
b11110011 :
b111 @
b111 B
b111 I
1#
#120000
0#
#125000
0-
0(
0'
0)
b11 @
b11 B
b11 I
b1111001 "
b1111001 2
b1111001 :
b11001 =
b11001 O
1*
b10 ;
b10 E
b111 8
1#
#130000
0#
#135000
1-
1(
1'
1)
b101 8
1#
#140000
0#
#145000
0F
0+
0-
0(
0'
0)
b1 @
b1 B
b1 I
b111100 "
b111100 2
b111100 :
b11100 =
b11100 O
b1 ;
b1 E
b111 8
1#
#150000
0#
#155000
b10111 <
b10111 C
b10111 G
11
17
16
b11 8
1#
#160000
0#
#165000
b1 <
b1 C
b1 G
1H
01
07
1-
1(
1'
06
1)
b1011111100 "
b1011111100 2
b1011111100 :
b10111 @
b10111 B
b10111 I
b101 8
1#
#170000
0#
#175000
0-
0(
0'
0)
b111 8
1,
b0 ;
b0 E
0*
b11110 =
b11110 O
b1101111110 "
b1101111110 2
b1101111110 :
b11011 @
b11011 B
b11011 I
1#
#180000
0#
#185000
1!
b110 8
1#
