nptel_eg/datapath_controlpath/GCD_computation_by_repeated_subtraction/GCD_controller.v
`timescale 1ns/1ps 
module GCD_controller (
    output reg LdA, LdB, sel1, sel2, sel_in, done,
    input wire lt, gt, eq, start, clk 
);

reg [2:0] state;
parameter   s0= 3'b000,
            s1= 3'b001,
            s2= 3'b010,
            s3= 3'b011,
            s4= 3'b100,
            s5= 3'b101;

always @(posedge clk) begin
    case (state)
        s0: if(start) state<= s1;
        s1: state<= s2;
        s2: begin
            if (eq) state<= s5;
            else if(lt) state<= s3;
            else if(gt) state<= s4; 
        end 
        s3: begin
            if(eq) state<= s5;
            else if(lt) state<= s3;
            else if(gt) state<= s4;
        end
        s4: begin
            if(eq) state<= s5;
            else if(lt) state<= s3;
            else if(gt) state<= s4;
        end
        s5: state<= s5;
        default: state<= s0;
    endcase
end

always @(state) begin
    case (state)
        s0: {LdA, LdB, sel1, sel2, sel_in, done}=6'b100010;
        s1: {LdA, LdB, sel1, sel2, sel_in, done}=6'b010010;
        s2: begin
            if(eq) {LdA, LdB, sel1, sel2, sel_in, done}=6'b000001;
            else if(lt) {LdA, LdB, sel1, sel2, sel_in, done}=6'b011000;
            else if(gt) {LdA, LdB, sel1, sel2, sel_in, done}=6'b100100;
        end
        s3: begin
            if(eq) {LdA, LdB, sel1, sel2, sel_in, done}=6'b000001;
            else if(lt) {LdA, LdB, sel1, sel2, sel_in, done}=6'b011000;
            else if(gt) {LdA, LdB, sel1, sel2, sel_in, done}=6'b100100;
        end
        s4: begin
            if(eq) {LdA, LdB, sel1, sel2, sel_in, done}=6'b000001;
            else if(lt) {LdA, LdB, sel1, sel2, sel_in, done}=6'b011000;
            else if(gt) {LdA, LdB, sel1, sel2, sel_in, done}=6'b100100;
        end
        s5: {LdA, LdB, sel1, sel2, sel_in, done}=6'b000001;

        default: {LdA, LdB, sel1, sel2, sel_in, done}=6'b000000;
    endcase
end

endmodule //GCD_controller

nptel_eg/datapath_controlpath/GCD_computation_by_repeated_subtraction/COMPARE.v
`timescale 1ns/1ps 
module COMPARE (
    output wire lt, gt, eq, 
    input wire [15:0] data1, data2
);

assign lt= data1<data2;
assign gt= data1>data2;
assign eq= data1==data2;
endmodule //COMPARE

nptel_eg/datapath_controlpath/GCD_computation_by_repeated_subtraction/SUB.v
`timescale 1ns/1ps 
module SUB (
    output reg [15:0] out,
    input  wire [15:0] in1, in2 
);

always @(*) begin
    out= in1-in2; 
end

endmodule //SUB

nptel_eg/datapath_controlpath/GCD_computation_by_repeated_subtraction/MUX.v
`timescale 1ns/1ps 
module MUX (
    output wire [15:0] out,
    input wire [15:0] in0, in1,
    input wire sel 
);

assign out= sel ? in1 : in0;

endmodule //MUX

nptel_eg/datapath_controlpath/GCD_computation_by_repeated_subtraction/PIPO.v
`timescale 1ns/1ps 
module PIPO (
    output reg [15:0] data_out,
    input wire [15:0] data_in,
    input wire load, clk 
);

always @(posedge clk) begin
    if(load) data_out<= data_in;
end

endmodule //PIPO

nptel_eg/datapath_controlpath/GCD_computation_by_repeated_subtraction/GCD_datapath.v
`timescale 1ns/1ps 
/*
data-path instantiates the fundamental functional blocks
1.PIPO
2.MUX
3.SUB
4.COMPARATOR
*/

`include "PIPO.v"
`include "MUX.v"
`include "SUB.v"
`include "COMPARE.v"

module GCD_datapath (
    output wire gt, lt, eq,
    output wire [15:0] GCD,
    input wire [15:0] data_in,
    input wire LdA, LdB, sel1, sel2, sel_in, clk 
);
wire [15:0] Aout, Bout, X, Y, Bus, SubOut;

assign GCD= Bus;

PIPO A(Aout, Bus, LdA, clk);
PIPO B(Bout, Bus, LdB, clk);
MUX MUX_in1(X, Aout, Bout, sel1);
MUX MUX_in2(Y, Aout, Bout, sel2);
MUX MUX_load(Bus, SubOut, data_in, sel_in);
SUB SB(SubOut, X, Y);
COMPARE COMP(lt, gt, eq, Aout, Bout);

endmodule //GCD_datapath

nptel_eg/datapath_controlpath/GCD_computation_by_repeated_subtraction/top.v
`timescale 1ns/1ps 
`include "GCD_datapath.v"
`include "GCD_controller.v"
//top module instantiating the fundamental units
module top (
    output wire done,
    output wire [15:0] GCD,
    input wire [15:0] data_in,
    input wire start, clk
);

wire LdA, LdB, sel1, sel2, sel_in, lt, gt, eq;
wire [15:0] BUS;

assign GCD= BUS;

GCD_datapath DAT(
    .gt(gt),
    .lt(lt),
    .eq(eq),
    .GCD(BUS),
    .data_in(data_in),
    .LdA(LdA),
    .LdB(LdB),
    .sel1(sel1),
    .sel2(sel2),
    .sel_in(sel_in),
    .clk(clk)
);
GCD_controller CTRL(
    .gt(gt),
    .lt(lt),
    .eq(eq),
    .start(start),
    .LdA(LdA),
    .LdB(LdB),
    .sel1(sel1),
    .sel2(sel2),
    .sel_in(sel_in),
    .clk(clk),
    .done(done)
);

endmodule //top

nptel_eg/datapath_controlpath/GCD_computation_by_repeated_subtraction/top_tb.v
`timescale 1ns/1ps 
`include "top.v"
module top_tb (
    
);

wire done;
wire [15:0] GCD;   
reg [15:0] data_in;
reg start, clk;

top t0(
    .done(done),
    .GCD(GCD),
    .data_in(data_in),
    .start(start),
    .clk(clk)
);

initial begin
    clk= 1'b0;
    forever #5 clk= ~clk;
end

initial begin
    $dumpfile("top_tb.vcd");
    $dumpvars(0, top_tb);

    start= 1'b1;
    #12 data_in= 16'd143;
    #10 data_in= 16'd78;
    #1000 $finish;
end


endmodule //top_tb

nptel_eg/datapath_controlpath/GCD_computation_by_repeated_subtraction/top_tb.vcd
$date
	Thu Nov 12 19:19:28 2020
$end
$version
	Icarus Verilog
$end
$timescale
	1ps
$end
$scope module top_tb $end
$var wire 1 ! done $end
$var wire 16 " GCD [15:0] $end
$var reg 1 # clk $end
$var reg 16 $ data_in [15:0] $end
$var reg 1 % start $end
$scope module t0 $end
$var wire 16 & GCD [15:0] $end
$var wire 1 # clk $end
$var wire 16 ' data_in [15:0] $end
$var wire 1 % start $end
$var wire 1 ( sel_in $end
$var wire 1 ) sel2 $end
$var wire 1 * sel1 $end
$var wire 1 + lt $end
$var wire 1 , gt $end
$var wire 1 - eq $end
$var wire 1 ! done $end
$var wire 1 . LdB $end
$var wire 1 / LdA $end
$var wire 16 0 BUS [15:0] $end
$scope module CTRL $end
$var wire 1 # clk $end
$var wire 1 % start $end
$var wire 1 + lt $end
$var wire 1 , gt $end
$var wire 1 - eq $end
$var reg 1 / LdA $end
$var reg 1 . LdB $end
$var reg 1 ! done $end
$var reg 1 * sel1 $end
$var reg 1 ) sel2 $end
$var reg 1 ( sel_in $end
$var reg 3 1 state [2:0] $end
$upscope $end
$scope module DAT $end
$var wire 16 2 GCD [15:0] $end
$var wire 1 / LdA $end
$var wire 1 . LdB $end
$var wire 1 # clk $end
$var wire 16 3 data_in [15:0] $end
$var wire 1 * sel1 $end
$var wire 1 ) sel2 $end
$var wire 1 ( sel_in $end
$var wire 1 + lt $end
$var wire 1 , gt $end
$var wire 1 - eq $end
$var wire 16 4 Y [15:0] $end
$var wire 16 5 X [15:0] $end
$var wire 16 6 SubOut [15:0] $end
$var wire 16 7 Bus [15:0] $end
$var wire 16 8 Bout [15:0] $end
$var wire 16 9 Aout [15:0] $end
$scope module A $end
$var wire 1 # clk $end
$var wire 1 / load $end
$var wire 16 : data_in [15:0] $end
$var reg 16 ; data_out [15:0] $end
$upscope $end
$scope module B $end
$var wire 1 # clk $end
$var wire 1 . load $end
$var wire 16 < data_in [15:0] $end
$var reg 16 = data_out [15:0] $end
$upscope $end
$scope module COMP $end
$var wire 16 > data1 [15:0] $end
$var wire 16 ? data2 [15:0] $end
$var wire 1 + lt $end
$var wire 1 , gt $end
$var wire 1 - eq $end
$upscope $end
$scope module MUX_in1 $end
$var wire 16 @ in0 [15:0] $end
$var wire 16 A in1 [15:0] $end
$var wire 1 * sel $end
$var wire 16 B out [15:0] $end
$upscope $end
$scope module MUX_in2 $end
$var wire 16 C in0 [15:0] $end
$var wire 16 D in1 [15:0] $end
$var wire 1 ) sel $end
$var wire 16 E out [15:0] $end
$upscope $end
$scope module MUX_load $end
$var wire 16 F in1 [15:0] $end
$var wire 1 ( sel $end
$var wire 16 G out [15:0] $end
$var wire 16 H in0 [15:0] $end
$upscope $end
$scope module SB $end
$var wire 16 I in1 [15:0] $end
$var wire 16 J in2 [15:0] $end
$var reg 16 K out [15:0] $end
$upscope $end
$upscope $end
$upscope $end
$upscope $end
$enddefinitions $end
#0
$dumpvars
bx K
bx J
bx I
bx H
bx G
bx F
bx E
bx D
bx C
bx B
bx A
bx @
bx ?
bx >
bx =
bx <
bx ;
bx :
bx 9
bx 8
bx 7
bx 6
bx 5
bx 4
bx 3
bx 2
bx 1
bx 0
x/
x.
x-
x,
x+
x*
x)
x(
bx '
bx &
1%
bx $
0#
bx "
x!
$end
#5000
1/
0.
0*
0)
1(
0!
b0 1
1#
#10000
0#
#12000
b10001111 "
b10001111 &
b10001111 0
b10001111 2
b10001111 7
b10001111 :
b10001111 <
b10001111 G
b10001111 $
b10001111 '
b10001111 3
b10001111 F
#15000
b0 6
b0 H
b0 K
0/
1.
b10001111 5
b10001111 B
b10001111 I
b10001111 4
b10001111 E
b10001111 J
b1 1
b10001111 9
b10001111 ;
b10001111 >
b10001111 @
b10001111 C
1#
#20000
0#
#22000
b1001110 "
b1001110 &
b1001110 0
b1001110 2
b1001110 7
b1001110 :
b1001110 <
b1001110 G
b1001110 $
b1001110 '
b1001110 3
b1001110 F
#25000
b1000001 6
b1000001 H
b1000001 K
b1001110 4
b1001110 E
b1001110 J
b1000001 "
b1000001 &
b1000001 0
b1000001 2
b1000001 7
b1000001 :
b1000001 <
b1000001 G
1/
0.
1)
0(
0+
1,
0-
b1001110 8
b1001110 =
b1001110 ?
b1001110 A
b1001110 D
b10 1
1#
#30000
0#
#35000
b1101 "
b1101 &
b1101 0
b1101 2
b1101 7
b1101 :
b1101 <
b1101 G
b1000001 4
b1000001 E
b1000001 J
b1101 6
b1101 H
b1101 K
0/
1.
1*
0)
b1001110 5
b1001110 B
b1001110 I
b100 1
1+
0,
b1000001 9
b1000001 ;
b1000001 >
b1000001 @
b1000001 C
1#
#40000
0#
#45000
b110100 "
b110100 &
b110100 0
b110100 2
b110100 7
b110100 :
b110100 <
b110100 G
b110100 6
b110100 H
b110100 K
b1101 4
b1101 E
b1101 J
b1000001 5
b1000001 B
b1000001 I
1/
0.
0*
1)
0+
1,
b1101 8
b1101 =
b1101 ?
b1101 A
b1101 D
b11 1
1#
#50000
0#
#55000
b100111 "
b100111 &
b100111 0
b100111 2
b100111 7
b100111 :
b100111 <
b100111 G
b100111 6
b100111 H
b100111 K
b110100 5
b110100 B
b110100 I
b100 1
b110100 9
b110100 ;
b110100 >
b110100 @
b110100 C
1#
#60000
0#
#65000
b11010 "
b11010 &
b11010 0
b11010 2
b11010 7
b11010 :
b11010 <
b11010 G
b11010 6
b11010 H
b11010 K
b100111 5
b100111 B
b100111 I
b100111 9
b100111 ;
b100111 >
b100111 @
b100111 C
1#
#70000
0#
#75000
b1101 "
b1101 &
b1101 0
b1101 2
b1101 7
b1101 :
b1101 <
b1101 G
b1101 6
b1101 H
b1101 K
b11010 5
b11010 B
b11010 I
b11010 9
b11010 ;
b11010 >
b11010 @
b11010 C
1#
#80000
0#
#85000
b0 "
b0 &
b0 0
b0 2
b0 7
b0 :
b0 <
b0 G
b0 6
b0 H
b0 K
b1101 5
b1101 B
b1101 I
0,
1-
b1101 9
b1101 ;
b1101 >
b1101 @
b1101 C
1#
#90000
0#
#95000
b0 "
b0 &
b0 0
b0 2
b0 7
b0 :
b0 <
b0 G
b0 4
b0 E
b0 J
b0 6
b0 H
b0 K
0/
0)
1!
b0 5
b0 B
b0 I
b101 1
1+
0-
b0 9
b0 ;
b0 >
b0 @
b0 C
1#
