nptel_eg/pipelining/pipe_ex.v
`timescale 1ns/1ps
//verilog code for pipeline modeling
module pipe_ex #(parameter N= 10) (
    output wire [N-1:0] F,
    input wire [N-1:0] A, B, C, D,
    input wire clk 
);

reg [N-1:0] L12_x1, L12_x2, L12_D, L23_x3, L23_D, L34_F;

assign F= L34_F;
//using separate always block
//**stage 1**
always @(posedge clk) begin
    L12_x1<= A+B;
    L12_x2<= C-D;
    L12_D<= D;
    end

//**stage 2**
always @(posedge clk) begin
    L23_x3<= L12_x1+L12_x2;
    L23_D<= L12_D;
end

//**stage 3**
always @(posedge clk) begin
    L34_F<= L23_x3*L23_D;
end

endmodule //pipe_ex

nptel_eg/pipelining/pipe_ex_tb.v
`timescale 1ns/1ps 
`include "pipe_ex.v"
module pipe_ex_tb (
    
);

parameter N=10;
wire [N-1:0] F;
reg [N-1:0] A, B, C, D;
reg clk;

pipe_ex p0(F, A, B, C, D, clk);

initial begin
    clk= 1'b0;
    forever #10 clk= !clk;
end

initial begin
    $dumpfile("pipe_ex_tb.vcd");
    $dumpvars(0, pipe_ex_tb);

    #5 {A, B, C, D}= {10'd10, 10'd12, 10'd6, 10'd3};
    #20 {A, B, C, D}= {10'd10, 10'd10, 10'd5, 10'd3};
    #20 {A, B, C, D}= {10'd20, 10'd11, 10'd1, 10'd4};
    #20 {A, B, C, D}= {10'd15, 10'd10, 10'd8, 10'd2};
    #20 {A, B, C, D}= {10'd8, 10'd15, 10'd5, 10'd0};
    #20 {A, B, C, D}= {10'd10, 10'd20, 10'd5, 10'd3};
    #20 {A, B, C, D}= {10'd10, 10'd10, 10'd30, 10'd1};
    #20 {A, B, C, D}= {10'd30, 10'd1, 10'd2, 10'd4};
    #60 $finish;
end
endmodule //pipe_ex_tb

nptel_eg/pipelining/pipe_ex_tb.vcd
$date
	Mon Nov 23 19:14:36 2020
$end
$version
	Icarus Verilog
$end
$timescale
	1ps
$end
$scope module pipe_ex_tb $end
$var wire 10 ! F [9:0] $end
$var reg 10 " A [9:0] $end
$var reg 10 # B [9:0] $end
$var reg 10 $ C [9:0] $end
$var reg 10 % D [9:0] $end
$var reg 1 & clk $end
$scope module p0 $end
$var wire 10 ' A [9:0] $end
$var wire 10 ( B [9:0] $end
$var wire 10 ) C [9:0] $end
$var wire 10 * D [9:0] $end
$var wire 10 + F [9:0] $end
$var wire 1 & clk $end
$var reg 10 , L12_D [9:0] $end
$var reg 10 - L12_x1 [9:0] $end
$var reg 10 . L12_x2 [9:0] $end
$var reg 10 / L23_D [9:0] $end
$var reg 10 0 L23_x3 [9:0] $end
$var reg 10 1 L34_F [9:0] $end
$upscope $end
$upscope $end
$enddefinitions $end
#0
$dumpvars
bx 1
bx 0
bx /
bx .
bx -
bx ,
bx +
bx *
bx )
bx (
bx '
0&
bx %
bx $
bx #
bx "
bx !
$end
#5000
b1010 "
b1010 '
b1100 #
b1100 (
b110 $
b110 )
b11 %
b11 *
#10000
b11 ,
b11 .
b10110 -
1&
#20000
0&
#25000
b1010 #
b1010 (
b101 $
b101 )
#30000
b11 /
b11001 0
b10 .
b10100 -
1&
#40000
0&
#45000
b10100 "
b10100 '
b1011 #
b1011 (
b1 $
b1 )
b100 %
b100 *
#50000
b100 ,
b1111111101 .
b11111 -
b10110 0
b1001011 !
b1001011 +
b1001011 1
1&
#60000
0&
#65000
b1111 "
b1111 '
b1010 #
b1010 (
b1000 $
b1000 )
b10 %
b10 *
#70000
b1000010 !
b1000010 +
b1000010 1
b100 /
b11100 0
b10 ,
b110 .
b11001 -
1&
#80000
0&
#85000
b1000 "
b1000 '
b1111 #
b1111 (
b101 $
b101 )
b0 %
b0 *
#90000
b0 ,
b101 .
b10111 -
b10 /
b11111 0
b1110000 !
b1110000 +
b1110000 1
1&
#100000
0&
#105000
b1010 "
b1010 '
b10100 #
b10100 (
b11 %
b11 *
#110000
b111110 !
b111110 +
b111110 1
b0 /
b11100 0
b11 ,
b10 .
b11110 -
1&
#120000
0&
#125000
b1010 #
b1010 (
b11110 $
b11110 )
b1 %
b1 *
#130000
b1 ,
b11101 .
b10100 -
b11 /
b100000 0
b0 !
b0 +
b0 1
1&
#140000
0&
#145000
b11110 "
b11110 '
b1 #
b1 (
b10 $
b10 )
b100 %
b100 *
#150000
b1100000 !
b1100000 +
b1100000 1
b1 /
b110001 0
b100 ,
b1111111110 .
b11111 -
1&
#160000
0&
#170000
b100 /
b11101 0
b110001 !
b110001 +
b110001 1
1&
#180000
0&
#190000
b1110100 !
b1110100 +
b1110100 1
1&
