nptel_eg/ALU_pipelining/pipe_ex2.v
`timescale 1ns/1ps 
module pipe_ex2 (
    output wire [15:0] Zout,
    input wire [3:0] rs1, rs2, rd, func,
    input wire [7:0] addr,
    input wire clk1, clk2
);

reg [15:0] L12_A, L12_B, L23_Z, L34_Z;
reg [3:0] L12_rd, L12_func, L23_rd;
reg [7:0] L12_addr, L23_addr, L34_addr;
reg [15:0] regbank [0:15];
reg [15:0] mem [0:255];

parameter   zero= 4'd0,
            one= 4'd1,
            two= 4'd2,
            three= 4'd3,
            four= 4'd4,
            five= 4'd5,
            six= 4'd6,
            seven= 4'd7,
            eight= 4'd8,
            nine= 4'd9,
            ten= 4'd10,
            eleven= 4'd11;

assign Zout= L34_Z;

//stage 1
always @(posedge clk1) begin
    L12_A<= regbank[rs1];
    L12_B<= regbank[rs2];
    L12_rd<= rd;
    L12_func<= func;
    L12_addr<= addr;
end

//stage 2
always @(negedge clk2) begin
    case (L12_func)
        zero: L23_Z<= L12_A + L12_B;
        one: L23_Z<= L12_A - L12_B;
        two: L23_Z<= L12_A * L12_B;
        three: L23_Z<= L12_A;
        four: L23_Z<= L12_B;
        five: L23_Z<= L12_A & L12_B;
        six: L23_Z<= L12_A | L12_B;
        seven: L23_Z<= L12_A ^ L12_B;
        eight: L23_Z<= -L12_A;
        nine: L23_Z<= -L12_B;
        ten: L23_Z<= L12_A>>1;
        eleven: L23_Z<= L12_A<<1;
        default: L23_Z<= 16'hxxxx;
    endcase
    L23_rd<= L12_rd;
    L23_addr<= L12_addr;
end

//stage 3
always @(posedge clk1) begin
    regbank[L23_rd]<= L23_Z;
    L34_Z<= L23_Z;
    L34_addr<= L23_addr;
end

//stage 4
always @(negedge clk2) begin
    mem[L34_addr]<= L34_Z;
end

endmodule //pipe_ex2

nptel_eg/ALU_pipelining/pipe_ex2_tb.v
`timescale 1ns/1ps 
`include "pipe_ex2.v"
module pipe_ex2_tb (
    
);

wire [15:0] Zout;
reg [3:0] rs1, rs2, rd, func;
reg [7:0] addr;
reg clk1, clk2;
integer k;
  
pipe_ex2 p0(Zout, rs1, rs2, rd, func, addr, clk1, clk2);

initial begin
    clk1= 0; clk2= 0;
    repeat(20) begin
        #5 clk1= 1; #5 clk1= 0;
        #5 clk2= 1; #5 clk2= 0;
    end
end

initial begin
    for (k= 0; k<16; k=k+1) begin
        p0.regbank[k]= k;
    end
end

initial begin
    for (k= 0; k<16; k= k+1) begin
        $display(p0.regbank[k]);
    end
end

initial begin
    #3 {rs1, rs2, rd, func, addr}= {4'd10, 4'd5, 4'd10, 4'd5, 8'd125};
    #20 {rs1, rs2, rd, func, addr}= {4'd12, 4'd8, 4'd12, 4'd5, 8'd126};
    #20 {rs1, rs2, rd, func, addr}= {4'd13, 4'd5, 4'd14, 4'd0, 8'd128};
    #20 {rs1, rs2, rd, func, addr}= {4'd7, 4'd3, 4'd13, 4'd11, 8'd127};
    #20 {rs1, rs2, rd, func, addr}= {4'd9, 4'd5, 4'd15, 4'd1, 8'd129};
end

initial begin
    $dumpfile("pipe_ex2_tb.vcd");
    $dumpvars(0, pipe_ex2_tb);

    #150 $finish; 
end
endmodule

nptel_eg/ALU_pipelining/pipe_ex2_tb.vcd
$date
	Tue Nov 24 19:17:12 2020
$end
$version
	Icarus Verilog
$end
$timescale
	1ps
$end
$scope module pipe_ex2_tb $end
$var wire 16 ! Zout [15:0] $end
$var reg 8 " addr [7:0] $end
$var reg 1 # clk1 $end
$var reg 1 $ clk2 $end
$var reg 4 % func [3:0] $end
$var reg 4 & rd [3:0] $end
$var reg 4 ' rs1 [3:0] $end
$var reg 4 ( rs2 [3:0] $end
$var integer 32 ) k [31:0] $end
$scope module p0 $end
$var wire 16 * Zout [15:0] $end
$var wire 8 + addr [7:0] $end
$var wire 1 # clk1 $end
$var wire 1 $ clk2 $end
$var wire 4 , func [3:0] $end
$var wire 4 - rd [3:0] $end
$var wire 4 . rs1 [3:0] $end
$var wire 4 / rs2 [3:0] $end
$var reg 16 0 L12_A [15:0] $end
$var reg 16 1 L12_B [15:0] $end
$var reg 8 2 L12_addr [7:0] $end
$var reg 4 3 L12_func [3:0] $end
$var reg 4 4 L12_rd [3:0] $end
$var reg 16 5 L23_Z [15:0] $end
$var reg 8 6 L23_addr [7:0] $end
$var reg 4 7 L23_rd [3:0] $end
$var reg 16 8 L34_Z [15:0] $end
$var reg 8 9 L34_addr [7:0] $end
$upscope $end
$upscope $end
$enddefinitions $end
#0
$dumpvars
bx 9
bx 8
bx 7
bx 6
bx 5
bx 4
bx 3
bx 2
bx 1
bx 0
bx /
bx .
bx -
bx ,
bx +
bx *
b10000 )
bx (
bx '
bx &
bx %
0$
0#
bx "
bx !
$end
#3000
b1010 '
b1010 .
b101 (
b101 /
b1010 &
b1010 -
b101 %
b101 ,
b1111101 "
b1111101 +
#5000
b1111101 2
b101 3
b1010 4
b101 1
b1010 0
1#
#10000
0#
#15000
1$
#20000
b1111101 6
b1010 7
b0 5
0$
#23000
b1100 '
b1100 .
b1000 (
b1000 /
b1100 &
b1100 -
b1111110 "
b1111110 +
#25000
b1111101 9
b0 !
b0 *
b0 8
b1111110 2
b1100 4
b1000 1
b1100 0
1#
#30000
0#
#35000
1$
#40000
b1111110 6
b1100 7
b1000 5
0$
#43000
b1101 '
b1101 .
b101 (
b101 /
b1110 &
b1110 -
b0 %
b0 ,
b10000000 "
b10000000 +
#45000
b10000000 2
b0 3
b1110 4
b101 1
b1101 0
b1111110 9
b1000 !
b1000 *
b1000 8
1#
#50000
0#
#55000
1$
#60000
b10000000 6
b1110 7
b10010 5
0$
#63000
b111 '
b111 .
b11 (
b11 /
b1101 &
b1101 -
b1011 %
b1011 ,
b1111111 "
b1111111 +
#65000
b10000000 9
b10010 !
b10010 *
b10010 8
b1111111 2
b1011 3
b1101 4
b11 1
b111 0
1#
#70000
0#
#75000
1$
#80000
b1111111 6
b1101 7
b1110 5
0$
#83000
b1001 '
b1001 .
b101 (
b101 /
b1111 &
b1111 -
b1 %
b1 ,
b10000001 "
b10000001 +
#85000
b10000001 2
b1 3
b1111 4
b101 1
b1001 0
b1111111 9
b1110 !
b1110 *
b1110 8
1#
#90000
0#
#95000
1$
#100000
b10000001 6
b1111 7
b100 5
0$
#105000
b10000001 9
b100 !
b100 *
b100 8
1#
